master733/__init__.py
master733-0.1.0.dist-info/METADATA
master733-0.1.0.dist-info/WHEEL
master733-0.1.0.dist-info/RECORD
